ollmcp/cli.py
ollmcp-0.26.0.dist-info/METADATA
ollmcp-0.26.0.dist-info/WHEEL
ollmcp-0.26.0.dist-info/entry_points.txt
ollmcp-0.26.0.dist-info/top_level.txt
ollmcp-0.26.0.dist-info/RECORD
