Metadata-Version: 2.4
Name: ollmcp
Version: 0.26.0
Summary: CLI for MCP Client for Ollama - An easy-to-use command for interacting with Ollama through MCP
Author: Jonathan Löwenstern
License-Expression: MIT
Project-URL: Homepage, https://github.com/jonigl/mcp-client-for-ollama
Project-URL: Issues, https://github.com/jonigl/mcp-client-for-ollama/issues
Requires-Python: >=3.10
Requires-Dist: mcp-client-for-ollama==0.26.0
